<?xml version="1.0"?>
<libosinfo version="0.0.1">
  <!-- Licensed under the GNU General Public License version 2 or later.
     See http://www.gnu.org/licenses/ for a copy of the license text -->
  <os id="http://slackware.com/slackware/current">
    <short-id>slackware-current</short-id>
    <name>Slackware -current</name>
    <name xml:lang="ka">Slackware -current</name>
    <name xml:lang="ko">&#xC2AC;&#xB799;&#xC6E8;&#xC5B4;-&#xD604;&#xC7AC;</name>
    <name xml:lang="uk">Slackware-current</name>
    <name xml:lang="tr">Slackware -current</name>
    <name xml:lang="pt_BR">Slackware -current</name>
    <name xml:lang="pl">Slackware -current</name>
    <name xml:lang="it">Slackware -current</name>
    <name xml:lang="id">Slackware -current</name>
    <name xml:lang="fr">Slackware -current</name>
    <version>current</version>
    <vendor>Slackware Linux Project</vendor>
    <vendor xml:lang="ka">Slackware Linux Project</vendor>
    <vendor xml:lang="ko">&#xC2AC;&#xB799;&#xC6E8;&#xC5B4; &#xB9AC;&#xB205;&#xC2A4; &#xD504;&#xB85C;&#xC81D;&#xD2B8;</vendor>
    <vendor xml:lang="uk">&#x41F;&#x440;&#x43E;&#x454;&#x43A;&#x442; Slackware Linux</vendor>
    <vendor xml:lang="tr">Slackware Linux Projesi</vendor>
    <vendor xml:lang="pt_BR">Projeto Slackware Linux</vendor>
    <vendor xml:lang="pl">Slackware Linux Project</vendor>
    <vendor xml:lang="it">Progetto Slackware Linux</vendor>
    <vendor xml:lang="id">Proyek Linux Slackware</vendor>
    <vendor xml:lang="fr">Projet Slackware Linux</vendor>
    <family>linux</family>
    <distro>slackware</distro>
    <upgrades id="http://slackware.com/slackware/14.2"/>
    <derives-from id="http://slackware.com/slackware/14.2"/>
  </os>
</libosinfo>
